podio/__init__.py
podio/client.py
podio/exceptions.py
podio_python-0.1.9.dist-info/LICENSE
podio_python-0.1.9.dist-info/METADATA
podio_python-0.1.9.dist-info/WHEEL
podio_python-0.1.9.dist-info/RECORD
