Metadata-Version: 2.1
Name: podio-python
Version: 0.1.9
Summary: API wrapper for Podio written in Python
Home-page: https://github.com/GearPlug/podio-python
License: MIT
Author: Juan Carlos Rios
Author-email: juankrios15@gmail.com
Requires-Python: >=3.7,<4.0
Classifier: License :: OSI Approved :: MIT License
Classifier: Programming Language :: Python :: 3
Classifier: Programming Language :: Python :: 3.7
Classifier: Programming Language :: Python :: 3.8
Classifier: Programming Language :: Python :: 3.9
Classifier: Programming Language :: Python :: 3.10
Classifier: Programming Language :: Python :: 3.11
Requires-Dist: requests (>=2.26.0,<3.0.0)
